romulus-0.0.1.data/data/my_data/data_file
sample/__init__.py
sample/package_data.dat
sample/simple.py
romulus-0.0.1.dist-info/LICENSE.txt
romulus-0.0.1.dist-info/METADATA
romulus-0.0.1.dist-info/WHEEL
romulus-0.0.1.dist-info/entry_points.txt
romulus-0.0.1.dist-info/top_level.txt
romulus-0.0.1.dist-info/RECORD
